discord_components_mirror
