Metadata-Version: 2.1
Name: discord-components-mirror
Version: 2.1.5
Summary: An unofficial library for discord components. Mirror only.
Home-page: https://github.com/kiki7000/discord.py-components
Author: kiki7000
Author-email: devkiki7000@gmail.com
License: MIT License
Platform: UNKNOWN
Classifier: Intended Audience :: Developers
Classifier: License :: OSI Approved :: MIT License
Classifier: Natural Language :: English
Classifier: Operating System :: OS Independent
Classifier: Programming Language :: Python :: 3
Classifier: Programming Language :: Python :: 3.6
Classifier: Programming Language :: Python :: 3.7
Classifier: Programming Language :: Python :: 3.8
Classifier: Programming Language :: Python :: 3.9
Classifier: Topic :: Internet
Classifier: Topic :: Software Development :: Libraries :: Python Modules
Classifier: Topic :: Software Development :: Libraries
Classifier: Topic :: Utilities
Requires-Python: >=3.6
Provides-Extra: lint
Provides-Extra: readthedocs
Provides-Extra: dev
License-File: LICENSE
